blue_chip/__init__.py
blue_chip/__main__.py
blue_chip/config/__init__.py
blue_chip/config/data.py
blue_chip/constants.py
blue_chip/tasks/__init__.py
blue_chip/tasks/formatting.py
blue_chip/tasks/linting.py
blue_chip-0.0.9.dist-info/entry_points.txt
blue_chip-0.0.9.dist-info/LICENSE
blue_chip-0.0.9.dist-info/WHEEL
blue_chip-0.0.9.dist-info/METADATA
blue_chip-0.0.9.dist-info/RECORD
