Metadata-Version: 2.1
Name: blue-chip
Version: 0.0.9
Summary: One click Python code quality package
Home-page: https://pypi.org/project/blue-chip/
License: GPLv2
Author: Gabriel Gore
Author-email: gabriel59kg@gmail.com
Requires-Python: >=3.6.2,<4.0.0
Classifier: Development Status :: 3 - Alpha
Classifier: License :: Other/Proprietary License
Classifier: Programming Language :: Python :: 3
Classifier: Programming Language :: Python :: 3.10
Classifier: Programming Language :: Python :: 3.7
Classifier: Programming Language :: Python :: 3.8
Classifier: Programming Language :: Python :: 3.9
Classifier: Topic :: Software Development :: Quality Assurance
Classifier: Topic :: Utilities
Requires-Dist: black (>=22.3.0,<23.0.0)
Requires-Dist: invoke
Requires-Dist: isort (>=5.10.1,<6.0.0)
Requires-Dist: prospector[with_pyroma] (>=1.2,<2.0)
Project-URL: Repository, https://github.com/Kilo59/blue-chip
